{"stat.useItem.minecraft.bow":15,"stat.walkOneCm":35539,"stat.killEntity.EntityHorse":1,"stat.useItem.minecraft.stone":64,"stat.horseOneCm":8457,"stat.pickup.minecraft.diamond_pickaxe":29,"stat.leaveGame":8,"stat.pickup.minecraft.arrow":1,"stat.useItem.minecraft.log":4,"stat.useItem.minecraft.tnt":25,"stat.pickup.minecraft.iron_shovel":1,"stat.killEntity.Creeper":2,"stat.pickup.minecraft.log":3,"stat.pickup.minecraft.diamond_sword":1,"stat.jump":147,"stat.swimOneCm":1474,"stat.useItem.minecraft.experience_bottle":44,"stat.useItem.minecraft.fire_charge":3,"stat.drop.minecraft.diamond_sword":4,"stat.crouchOneCm":1,"achievement.mineWood":1,"stat.useItem.minecraft.redstone_torch":25,"stat.killEntity.Squid":1,"stat.sprintOneCm":660,"achievement.exploreAllBiomes":{"value":0,"progress":["Roofed Forest M","Roofed Forest","Birch Forest","Plains","Cold Beach","River","Forest","Ocean","Desert","Mega Taiga","Extreme Hills","Swampland","Deep Ocean"]},"stat.killEntity.Skeleton":3,"stat.useItem.minecraft.dispenser":1,"achievement.openInventory":263,"stat.killEntity.Chicken":4,"stat.useItem.minecraft.flint_and_steel":1,"stat.damageTaken":840,"stat.dispenserInspected":1,"stat.mobKills":25,"stat.pickup.minecraft.cobblestone":2,"stat.flyOneCm":294646,"stat.deaths":3,"stat.drop":4,"stat.playOneMinute":488149,"stat.killEntity.Sheep":7,"stat.sneakTime":307,"stat.killEntity.Zombie":2,"stat.timeSinceDeath":204931,"stat.pickup.minecraft.dispenser":1,"stat.useItem.minecraft.spawn_egg":72,"stat.killEntity.Pig":5,"stat.diveOneCm":9497}